freightcom_lib/__init__.py
freightcom_lib/error.py
freightcom_lib/quote_reply.py
freightcom_lib/quote_request.py
freightcom_lib/shipment_cancel_reply.py
freightcom_lib/shipment_cancel_request.py
freightcom_lib/shipping_reply.py
freightcom_lib/shipping_request.py
purplship/mappers/freightcom/__init__.py
purplship/mappers/freightcom/mapper.py
purplship/mappers/freightcom/proxy.py
purplship/mappers/freightcom/settings.py
purplship/providers/freightcom/__init__.py
purplship/providers/freightcom/error.py
purplship/providers/freightcom/quote.py
purplship/providers/freightcom/shipping.py
purplship/providers/freightcom/units.py
purplship/providers/freightcom/utils.py
purplship/providers/freightcom/void_shipment.py
purplship.freightcom-2022.2.dist-info/LICENSE
purplship.freightcom-2022.2.dist-info/WHEEL
purplship.freightcom-2022.2.dist-info/METADATA
purplship.freightcom-2022.2.dist-info/RECORD
