Metadata-Version: 2.1
Name: purplship.freightcom
Version: 2022.2
Summary: Freightcom purplship extension
Home-page: https://github.com/purplship/purplship/tree/main/sdk/vendors/freightcom
License: Apache-2.0
Author: Purplship
Author-email: hello@purplship.com
Requires-Python: >=3.7,<4.0
Classifier: Intended Audience :: Developers
Classifier: License :: OSI Approved :: Apache Software License
Classifier: Operating System :: OS Independent
Classifier: Programming Language :: Python :: 3
Classifier: Programming Language :: Python :: 3.10
Classifier: Programming Language :: Python :: 3.7
Classifier: Programming Language :: Python :: 3.8
Classifier: Programming Language :: Python :: 3.9
Requires-Dist: purplship
Project-URL: Repository, https://github.com/purplship/purplship
